mypackage/__init__.py
mypackage/__main__.py
mypackage_tatusis-0.1.0.dist-info/licenses/LICENSE
mypackage_tatusis-0.1.0.dist-info/METADATA
mypackage_tatusis-0.1.0.dist-info/WHEEL
mypackage_tatusis-0.1.0.dist-info/top_level.txt
mypackage_tatusis-0.1.0.dist-info/RECORD
