Metadata-Version: 2.4
Name: mypackage_tatusis
Version: 0.1.0
Summary: My Python package
Author-email: Rafael Ferreira <rafaelsferreira@icloud.com>
License-Expression: MIT
Project-URL: Homepage, https://github.com/tatusis/mypackage
Project-URL: Bug Tracker, https://github.com/tatusis/mypackage/issues
Requires-Python: >=3.12
License-File: LICENSE
Dynamic: license-file
